gps_py3_shim/__init__.py
gps_py3_shim/client.py
gps_py3_shim/fake.py
gps_py3_shim/gps.py
gps_py3_shim/misc.py
gps_py3_shim-3.17.1.dist-info/DESCRIPTION.rst
gps_py3_shim-3.17.1.dist-info/LICENSE.txt
gps_py3_shim-3.17.1.dist-info/METADATA
gps_py3_shim-3.17.1.dist-info/RECORD
gps_py3_shim-3.17.1.dist-info/WHEEL
gps_py3_shim-3.17.1.dist-info/metadata.json
gps_py3_shim-3.17.1.dist-info/top_level.txt
