Metadata-Version: 2.0
Name: gps-py3-shim
Version: 3.17.1
Summary: gpsd client library (python3 port)
Home-page: https://github.com/teyrana/gpsd-python3
Author: Daniel Williams
Author-email: equipoise@gmail.com
License: BSD License (3-Clause)
Keywords: gps ais gpsd python3
Platform: UNKNOWN
Classifier: Development Status :: 4 - Beta
Classifier: Environment :: Console
Classifier: Intended Audience :: Developers
Classifier: Intended Audience :: Other Audience
Classifier: Intended Audience :: Science/Research
Classifier: License :: OSI Approved :: BSD License
Classifier: Natural Language :: English
Classifier: Operating System :: OS Independent
Classifier: Operating System :: POSIX
Classifier: Operating System :: POSIX :: Linux
Classifier: Programming Language :: Python :: 3
Classifier: Programming Language :: Python :: 3.5
Classifier: Programming Language :: Python :: 3.6
Classifier: Topic :: Scientific/Engineering
Classifier: Topic :: Scientific/Engineering :: GIS
